<?xml version="1.0"?>
<dataroot>
	<Table_Data_KOR>
		<FieldName_0>Tblidx</FieldName_0>
		<FieldName_1>Name</FieldName_1>
		<FieldName_2>Loc_X</FieldName_2>
		<FieldName_3>Loc_Y</FieldName_3>
		<FieldName_4>Loc_Z</FieldName_4>
		<FieldName_5>Dir_X</FieldName_5>
		<FieldName_6>Dir_Y</FieldName_6>
		<FieldName_7>Dir_Z</FieldName_7>
		<FieldName_8>Func</FieldName_8>
		<FieldName_9>Min_X</FieldName_9>
		<FieldName_10>Min_Y</FieldName_10>
		<FieldName_11>Min_Z</FieldName_11>
		<FieldName_12>Max_X</FieldName_12>
		<FieldName_13>Max_Y</FieldName_13>
		<FieldName_14>Max_Z</FieldName_14>
		<FieldName_15>DefMainState</FieldName_15>
		<FieldName_16>DefSubState</FieldName_16>
		<FieldName_17>State1</FieldName_17>
		<FieldName_18>State2</FieldName_18>
		<FieldName_19>State3</FieldName_19>
		<FieldName_20>State4</FieldName_20>
		<FieldName_21>State5</FieldName_21>
		<FieldName_22>State6</FieldName_22>
		<FieldName_23>State7</FieldName_23>
		<FieldName_24>State8</FieldName_24>
		<FieldName_25>State9</FieldName_25>
		<FieldName_26>State10</FieldName_26>
		<FieldName_27>Click_Sound1</FieldName_27>
		<FieldName_28>Click_Sound2</FieldName_28>
		<FieldName_29>Click_Sound3</FieldName_29>
		<FieldName_30>Click_Sound4</FieldName_30>
		<FieldName_31>Click_Sound5</FieldName_31>
		<FieldName_32>Click_Sound6</FieldName_32>
		<FieldName_33>Click_Sound7</FieldName_33>
		<FieldName_34>Click_Sound8</FieldName_34>
		<FieldName_35>Click_Sound9</FieldName_35>
		<FieldName_36>Click_Sound10</FieldName_36>
		<FieldName_37>Boundry_Distance</FieldName_37>
		<FieldName_38>ModelName</FieldName_38>
		<FieldName_39>Note</FieldName_39>
		<FieldName_40>Contents_Tblidx</FieldName_40>
		<FieldName_41>Object_Direction_Index</FieldName_41>
		<FieldName_42>MinQuestId</FieldName_42>
		<FieldName_43>MaxQuestId</FieldName_43>
	</Table_Data_KOR>
	<Table_Data_KOR>
		<TblIdx>1</TblIdx>
		<Name>-1</Name>
		<Loc_X>391.320007</Loc_X>
		<Loc_Y>-91.980003</Loc_Y>
		<Loc_Z>146.020004</Loc_Z>
		<Dir_X>0.000000</Dir_X>
		<Dir_Y>0.000000</Dir_Y>
		<Dir_Z>1.000000</Dir_Z>
		<Func>1</Func>
		<Min_X>389.290009</Min_X>
		<Min_Y>-91.769997</Min_Y>
		<Min_Z>144.550003</Min_Z>
		<Max_X>393.339996</Max_X>
		<Max_Y>-87.019997</Max_Y>
		<Max_Z>147.490005</Max_Z>
		<DefMainState>0</DefMainState>
		<DefSubState>1</DefSubState>
		<State1>1</State1>
		<State2>3</State2>
		<State3>255</State3>
		<State4>255</State4>
		<State5>255</State5>
		<State6>255</State6>
		<State7>255</State7>
		<State8>255</State8>
		<State9>255</State9>
		<State10>255</State10>
		<Click_Sound1>0</Click_Sound1>
		<Click_Sound2>-3</Click_Sound2>
		<Click_Sound3>-3</Click_Sound3>
		<Click_Sound4>-3</Click_Sound4>
		<Click_Sound5>-3</Click_Sound5>
		<Click_Sound6>-3</Click_Sound6>
		<Click_Sound7>-3</Click_Sound7>
		<Click_Sound8>-3</Click_Sound8>
		<Click_Sound9>-3</Click_Sound9>
		<Click_Sound10>-3</Click_Sound10>
		<Boundry_Distance>3</Boundry_Distance>
		<ModelName>TLQ_T_TIMECRACK_001</ModelName>
		<Note>0</Note>
		<Contents_Tblidx>1</Contents_Tblidx>
		<Object_Direction_Index>-1</Object_Direction_Index>
		<MinQuestId>65535</MinQuestId>
		<MaxQuestId>65535</MaxQuestId>
	</Table_Data_KOR>
</dataroot>
